PyQt6In/__init__.py
PyQt6In/core.py
PyQt6In-0.1.2.dist-info/METADATA
PyQt6In-0.1.2.dist-info/WHEEL
PyQt6In-0.1.2.dist-info/top_level.txt
PyQt6In-0.1.2.dist-info/RECORD
