Metadata-Version: 2.1
Name: PyQt6In
Version: 0.1.2
Summary: libary
Author: Berg679
Author-email: redmigardo@gmail.com
Classifier: Programming Language :: Python :: 3
Classifier: License :: OSI Approved :: MIT License
Classifier: Operating System :: OS Independent
Requires-Python: >=3.6
